notion_cli_list_manager/__init__.py
notion_cli_list_manager/main.py
notion_cli_list_manager/page.py
notion_cli_list_manager/utils.py
notion_cli_list_manager-0.1.6.dist-info/entry_points.txt
notion_cli_list_manager-0.1.6.dist-info/LICENSE
notion_cli_list_manager-0.1.6.dist-info/WHEEL
notion_cli_list_manager-0.1.6.dist-info/METADATA
notion_cli_list_manager-0.1.6.dist-info/RECORD
