Metadata-Version: 2.1
Name: notion-cli-list-manager
Version: 0.1.6
Summary: A simple command-line tool for managing Notion databases.
Home-page: https://github.com/jacksalici/notion-cli-list-manager
License: MIT
Keywords: Notion,CLI,todo manager
Author: Jack Salici
Requires-Python: >=3.8,<4.0
Classifier: License :: OSI Approved :: MIT License
Classifier: Programming Language :: Python :: 3
Classifier: Programming Language :: Python :: 3.10
Classifier: Programming Language :: Python :: 3.8
Classifier: Programming Language :: Python :: 3.9
Requires-Dist: colorama (>=0.4.4,<0.5.0)
Requires-Dist: prettytable (>=2.5.0,<3.0.0)
Requires-Dist: requests (>=2.26.0,<3.0.0)
Requires-Dist: toml (>=0.10.2,<0.11.0)
Requires-Dist: typer (>=0.4.0,<0.5.0)
Project-URL: Documentation, https://github.com/jacksalici/notion-cli-list-manager/wiki
Project-URL: Repository, https://github.com/jacksalici/notion-cli-list-manager
